pylapy/__init__.py
pylapy/cost_extension.py
pylapy/py.typed
pylapy/shape_extension.py
pylapy/solver.py
pylapy/sparse.py
pylapy-1.1.0.dist-info/licenses/LICENSE
pylapy-1.1.0.dist-info/METADATA
pylapy-1.1.0.dist-info/WHEEL
pylapy-1.1.0.dist-info/top_level.txt
pylapy-1.1.0.dist-info/RECORD
