Metadata-Version: 2.4
Name: pylapy
Version: 1.1.0
Summary: Pythonic wrapper around Linear Assignement Problem solvers
Home-page: https://github.com/raphaelreme/pylapy
Author: Raphael Reme
Author-email: raphaelreme-dev@protonmail.com
License: MIT
Keywords: lap,linear programming,optimization,association problem
Classifier: Development Status :: 4 - Beta
Classifier: License :: OSI Approved :: MIT License
Classifier: Natural Language :: English
Classifier: Operating System :: OS Independent
Classifier: Programming Language :: Python :: 3.9
Classifier: Programming Language :: Python :: 3.10
Classifier: Programming Language :: Python :: 3.11
Classifier: Programming Language :: Python :: 3.12
Classifier: Programming Language :: Python :: 3.13
Requires-Python: >=3.9
License-File: LICENSE
Requires-Dist: numpy
Provides-Extra: lap
Requires-Dist: lapx; extra == "lap"
Provides-Extra: lapjv
Requires-Dist: lapjv; extra == "lapjv"
Provides-Extra: lapsolver
Requires-Dist: lapx; extra == "lapsolver"
Provides-Extra: scipy
Requires-Dist: scipy; extra == "scipy"
Provides-Extra: sparse
Requires-Dist: scipy; extra == "sparse"
Requires-Dist: numba; extra == "sparse"
Dynamic: license-file
